{
    "34S" : {
        
            "chestWidth": {"name" : "Chest width","min": 37.5, "default": 39.00, "max": 40.50},
            "waistWidth": {"name":"Waist width","min": 31.50, "default": 34.00, "max": 37.00},
            "jacketLength": {"name":"Jacket length","min": 22.75, "default": 27.50, "max": 31.50},
            "sleeveLengthRight": {"name":"Sleeve length right","min": 19.00, "default": 23.00, "max": 27.00},
            "sleeveLengthLeft": {"name":"Sleeve length left","min": 19.00, "default": 23.00, "max": 27.00},
            "hipWidth": {"name": "Hip Width" ,"min": 15.00, "default": 17.00, "max": 18.75},
            "shoulderWidth": {"name": "Shoulder width", "min": 7.50, "default": 8.25, "max": 8.75},
            "backWidth": {"name":"Back width","min": 8.50, "default": 9.25, "max": 10.00},
            "ventLength": {"name":"Vent length","min": 27.75, "default": 28.75, "max": 30.00},
            "frontLength": {"name":"Front length","min": 13.00, "default": 14.00, "max": 15.00},
            "bicepAround": {"name":"Bicep around","min": 9.50, "default": 11.00, "max": 12.50},
            "sleeveEdgeWidth": {"name":"Sleeve edge width","min": -2.00, "default": 0.00, "max": 2.00},
            "posture": {"name":"Posture","min": -2.00, "default": 0.00, "max": 1.00},
            "shoulderHeightRight": {"name":"Shoulder height right","min": -2.00, "default": 0.00, "max": 1.00},
            "shoulderHeightLeft": {"name":"Shoulder height right","min": -2.00, "default": 0.00, "max": 1.00}
         }
    ,
    "36S" : { 
               "chestWidth": {"name" : "Chest width","min": 39, "default": 40.50, "max": 42.00},
               "waistWidth": {"name":"Waist width","min": 33, "default": 35.50, "max": 38.50},
               "jacketLength": {"name":"Jacket length","min": 23.25, "default": 28.00, "max": 31.75},
               "sleeveLengthRight": {"name":"Sleeve length right","min": 19.50, "default": 23.50, "max": 27.50},
               "sleeveLengthLeft": {"name":"Sleeve length left","min": 19.50, "default": 23.50, "max": 27.50},
               "hipWidth": {"name": "Hip Width" ,"min": 15.50, "default": 17.50, "max": 19.25},
               "shoulderWidth": {"name": "Shoulder width", "min": 7.75, "default": 8.50, "max": 9.00},
               "backWidth": {"name":"Back width","min": 8.50, "default": 9.50, "max": 10.25},
               "ventLength": {"name":"Vent length","min": 28.25, "default": 29.25, "max": 30.50},
               "frontLength": {"name":"Front length","min": 14, "default": 15, "max": 15.50},
               "bicepAround": {"name":"Bicep around","min": 9.50, "default": 11, "max": 12.50},
               "sleeveEdgeWidth": {"name":"Sleeve edge width","min": -2, "default": 0, "max": 2},
               "posture": {"name":"Posture","min": -2, "default": 0, "max": 1},
               "shoulderHeightRight": {"name":"Shoulder height right","min": -2, "default": 0, "max": 1},
               "shoulderHeightLeft": {"name":"Shoulder height right","min": -2, "default": 0, "max": 1}
            }
    ,
    "38S":{
        
           "chestWidth": {"name" : "Chest width","min": 41, "default": 42.00, "max": 43.50},
           "waistWidth": {"name":"Waist width","min": 35, "default": 37.00, "max": 40.00},
           "jacketLength": {"name":"Jacket length","min": 23.5, "default": 28.5, "max": 32.25},
           "sleeveLengthRight": {"name":"Sleeve length right","min": 19.75, "default": 23.75, "max": 27.75},
           "sleeveLengthLeft": {"name":"Sleeve length left","min": 19.75, "default": 23.75, "max": 27.75},
           "hipWidth": {"name": "Hip Width" ,"min": 15.75, "default": 17.75, "max": 19.50},
           "shoulderWidth": {"name": "Shoulder width", "min": 8, "default": 8.50, "max": 9.25},
           "backWidth": {"name":"Back width","min": 8.5, "default": 9.50, "max": 10.25},
           "ventLength": {"name":"Vent length","min": 28.5, "default": 29.50, "max": 30.75},
           "frontLength": {"name":"Front length","min": 15, "default": 15.50, "max": 16.50},
           "bicepAround": {"name":"Bicep around","min": 10, "default": 11.00, "max": 12.50},
           "sleeveEdgeWidth": {"name":"Sleeve edge width","min": -2, "default": 0.00, "max": 2.00},
           "posture": {"name":"Posture","min": -2, "default": 0.00, "max": 1.00},
           "shoulderHeightRight": {"name":"Shoulder height right","min": -2, "default": 0.00, "max": 1.00},
           "shoulderHeightLeft": {"name":"Shoulder height right","min": -2, "default": 0.00, "max": 1.00}
        }
    ,
    "40S" : {
        
           "chestWidth": {"name" : "Chest width","min": 42.5, "default": 43.50, "max": 45.00},
           "waistWidth": {"name":"Waist width","min": 36.50, "default": 38.50, "max": 41.50},
           "jacketLength": {"name":"Jacket length","min": 24.00, "default": 28.75, "max": 32.50},
           "sleeveLengthRight": {"name":"Sleeve length right","min": 20.25, "default": 24.25, "max": 28.25},
           "sleeveLengthLeft": {"name":"Sleeve length left","min": 20.25, "default": 24.25, "max": 28.25},
           "hipWidth": {"name": "Hip Width" ,"min": 16.25, "default": 18.25, "max": 20.00},
           "shoulderWidth": {"name": "Shoulder width", "min": 8.25, "default": 8.75, "max": 9.50},
           "backWidth": {"name":"Back width","min": 8.75, "default": 9.50, "max": 10.50},
           "ventLength": {"name":"Vent length","min": 29.00, "default": 30.00, "max": 31.25},
           "frontLength": {"name":"Front length","min": 15.50, "default": 16.50, "max": 17.00},
           "bicepAround": {"name":"Bicep around","min": 10.50, "default": 11.50, "max": 13.00},
           "sleeveEdgeWidth": {"name":"Sleeve edge width","min": -2.00, "default": 0.00, "max": 2.00},
           "posture": {"name":"Posture","min": -2.00, "default": 0.00, "max": 1.00},
           "shoulderHeightRight": {"name":"Shoulder height right","min": -2.00, "default": 0.00, "max": 1.00},
           "shoulderHeightLeft": {"name":"Shoulder height right","min": -2.00, "default": 0.00, "max": 1.00}
        }
    ,
    "42S": {
        
           "chestWidth": {"name" : "Chest width","min": 44, "default": 45.00, "max": 47.00},
           "waistWidth": {"name":"Waist width","min": 37.50, "default": 40.00, "max": 43.00},
           "jacketLength": {"name":"Jacket length","min": 24.50, "default": 29.25, "max": 33.00},
           "sleeveLengthRight": {"name":"Sleeve length right","min": 20.50, "default": 24.50, "max": 28.50},
           "sleeveLengthLeft": {"name":"Sleeve length left","min": 20.50, "default": 24.50, "max": 28.50},
           "hipWidth": {"name": "Hip Width" ,"min": 16.50, "default": 18.50, "max": 20.50},
           "shoulderWidth": {"name": "Shoulder width", "min": 8.50, "default": 9.00, "max": 9.50},
           "backWidth": {"name":"Back width","min": 9.00, "default": 9.75, "max": 10.50},
           "ventLength": {"name":"Vent length","min": 29.50, "default": 30.50, "max": 31.50},
           "frontLength": {"name":"Front length","min": 16.50, "default": 17.00, "max": 18.00},
           "bicepAround": {"name":"Bicep around","min": 10.50, "default": 11.50, "max": 13.00},
           "sleeveEdgeWidth": {"name":"Sleeve edge width","min": -2.00, "default": 0.00, "max": 2.00},
           "posture": {"name":"Posture","min": -2.00, "default": 0.00, "max": 1.00},
           "shoulderHeightRight": {"name":"Shoulder height right","min": -2.00, "default": 0.00, "max": 1.00},
           "shoulderHeightLeft": {"name":"Shoulder height right","min": -2.00, "default": 0.00, "max": 1.00}
        }
    ,
      "44S" : {
        
           "chestWidth": {"name" : "Chest width","min": 45.5, "default": 47.00, "max": 48.50},
           "waistWidth": {"name":"Waist width","min": 39.00, "default": 41.50, "max": 45.00},
           "jacketLength": {"name":"Jacket length","min": 24.75, "default": 29.50, "max": 33.50},
           "sleeveLengthRight": {"name":"Sleeve length right","min": 20.75, "default": 24.75, "max": 28.75},
           "sleeveLengthLeft": {"name":"Sleeve length left","min": 20.75, "default": 24.75, "max": 28.75},
           "hipWidth": {"name": "Hip Width" ,"min": 17.00, "default": 18.75, "max": 20.75},
           "shoulderWidth": {"name": "Shoulder width", "min": 8.75, "default": 9.50, "max": 10.00},
           "backWidth": {"name":"Back width","min": 9.00, "default": 9.75, "max": 10.50},
           "ventLength": {"name":"Vent length","min": 29.75, "default": 30.75, "max": 31.75},
           "frontLength": {"name":"Front length","min": 17.00, "default": 17.50, "max": 18.50},
           "bicepAround": {"name":"Bicep around","min": 11.00, "default": 12.00, "max": 13.00},
           "sleeveEdgeWidth": {"name":"Sleeve edge width","min": -2.00, "default": 0.00, "max": 2.00},
           "posture": {"name":"Posture","min": -2.00, "default": 0.00, "max": 2.00},
           "shoulderHeightRight": {"name":"Shoulder height right","min": -2.00, "default": 0.00, "max": 1.00},
           "shoulderHeightLeft": {"name":"Shoulder height right","min": -2.00, "default": 0.00, "max": 1.00}
        }
    ,
    "46S": {
        
           "chestWidth": {"name" : "Chest width","min": 47, "default": 48.50, "max": 50.00},
           "waistWidth": {"name":"Waist width","min": 41, "default": 43.00, "max": 46.50},
           "jacketLength": {"name":"Jacket length","min": 25.25, "default": 30.00, "max": 33.75},
           "sleeveLengthRight": {"name":"Sleeve length right","min": 21, "default": 25.00, "max": 29.00},
           "sleeveLengthLeft": {"name":"Sleeve length left","min": 21, "default": 25.00, "max": 29.00},
           "hipWidth": {"name": "Hip Width" ,"min": 17, "default": 19.25, "max": 21.25},
           "shoulderWidth": {"name": "Shoulder width", "min": 9, "default": 9.50, "max": 10.25},
           "backWidth": {"name":"Back width","min": 9, "default": 9.50, "max": 10.25},
           "ventLength": {"name":"Vent length","min": 9, "default": 9.25, "max": 10.00},
           "frontLength": {"name":"Front length","min": 9, "default": 10.00, "max": 10.75},
           "bicepAround": {"name":"Bicep around","min": 30, "default": 31.25, "max": 32.25},
           "sleeveEdgeWidth": {"name":"Sleeve edge width","min": 17, "default": 18.50, "max": 19.00},
           "posture": {"name":"Posture","min": -2, "default": 0, "max": 2},
           "shoulderHeightRight": {"name":"Shoulder height right","min": -2, "default": 0, "max": 1},
           "shoulderHeightLeft": {"name":"Shoulder height right","min": -2, "default": 0, "max": 1}
        }
    ,
    "48S" : {
        
           "chestWidth": {"name" : "Chest width","min": 49, "default": 50.00, "max": 51.50},
           "waistWidth": {"name":"Waist width","min": 42.50, "default": 45.00, "max": 48.00},
           "jacketLength": {"name":"Jacket length","min": 25.50, "default": 30.50, "max": 34.25},
           "sleeveLengthRight": {"name":"Sleeve length right","min": 21.25, "default": 25.25, "max": 29.25},
           "sleeveLengthLeft": {"name":"Sleeve length left","min": 21.25, "default": 25.25, "max": 29.25},
           "hipWidth": {"name": "Hip Width" ,"min": 46.00, "default": 48.50, "max": 51.50},
           "shoulderWidth": {"name": "Shoulder width", "min": 17.75, "default": 19.50, "max": 21.50},
           "backWidth": {"name":"Back width","min": 9.25, "default": 9.75, "max": 10.50},
           "ventLength": {"name":"Vent length","min": 9.25, "default": 10.00, "max": 10.75},
           "frontLength": {"name":"Front length","min": 30.50, "default": 31.50, "max": 32.50},
           "bicepAround": {"name":"Bicep around","min": 18.50, "default": 19.00, "max": 20.00},
           "sleeveEdgeWidth": {"name":"Sleeve edge width","min": 11.00, "default": 12.50, "max": 13.50},
           "posture": {"name":"Posture","min": -2.00, "default": 0.00, "max": 2.00},
           "shoulderHeightRight": {"name":"Shoulder height right","min": -2.00, "default": 0.00, "max": 1.00},
           "shoulderHeightLeft": {"name":"Shoulder height right","min": -2.00, "default": 0.00, "max": 1.00}
        }
    ,
    "50S":{
        
           "chestWidth": {"name" : "Chest width","min": 50.5, "default": 51.50, "max": 53.00},
           "waistWidth": {"name":"Waist width","min": 44.00, "default": 46.50, "max": 49.50},
           "jacketLength": {"name":"Jacket length","min": 26.00, "default": 30.75, "max": 34.50},
           "sleeveLengthRight": {"name":"Sleeve length right","min": 21.50, "default": 25.50, "max": 29.50},
           "sleeveLengthLeft": {"name":"Sleeve length left","min": 21.50, "default": 25.50, "max": 29.50},
           "hipWidth": {"name": "Hip Width" ,"min": 47.50, "default": 50.00, "max": 53.00},
           "shoulderWidth": {"name": "Shoulder width", "min": 18.25, "default": 20.00, "max": 22.00},
           "backWidth": {"name":"Back width","min": 9.50, "default": 10.00, "max": 10.50},
           "ventLength": {"name":"Vent length","min": 9.50, "default": 10.25, "max": 11.00},
           "frontLength": {"name":"Front length","min": 31.00, "default": 31.75, "max": 33.00},
           "bicepAround": {"name":"Bicep around","min": 19.00, "default": 20.00, "max": 21.00},
           "sleeveEdgeWidth": {"name":"Sleeve edge width","min": 11.50, "default": 12.50, "max": 14.00},
           "posture": {"name":"Posture","min": -2.00, "default": 0.00, "max": 2.00},
           "shoulderHeightRight": {"name":"Shoulder height right","min": -2.00, "default": 0.00, "max": 1.00},
           "shoulderHeightLeft": {"name":"Shoulder height right","min": -2.00, "default": 0.00, "max": 1.00}
        }
    ,
    "52S":{
        
           "chestWidth": {"name" : "Chest width","min": 52, "default": 53.00, "max": 55.00},
           "waistWidth": {"name":"Waist width","min": 45.50, "default": 48.00, "max": 51.00},
           "jacketLength": {"name":"Jacket length","min": 26.25, "default": 31.00, "max": 34.75},
           "sleeveLengthRight": {"name":"Sleeve length right","min": 21.50, "default": 25.50, "max": 29.50},
           "sleeveLengthLeft": {"name":"Sleeve length left","min": 21.50, "default": 25.50, "max": 29.50},
           "hipWidth": {"name": "Hip Width" ,"min": 49.00, "default": 51.50, "max": 55.00},
           "shoulderWidth": {"name": "Shoulder width", "min": 18.50, "default": 20.50, "max": 22.50},
           "backWidth": {"name":"Back width","min": 9.50, "default": 10.25, "max": 10.75},
           "ventLength": {"name":"Vent length","min": 9.50, "default": 10.50, "max": 11.25},
           "frontLength": {"name":"Front length","min": 31.25, "default": 32.00, "max": 33.25},
           "bicepAround": {"name":"Bicep around","min": 20.00, "default": 21.00, "max": 21.50},
           "sleeveEdgeWidth": {"name":"Sleeve edge width","min": 11.50, "default": 12.50, "max": 14.00},
           "posture": {"name":"Posture","min": -2.00, "default": 0.00, "max": 2.00},
           "shoulderHeightRight": {"name":"Shoulder height right","min": -2.00, "default": 0.00, "max": 1.00},
           "shoulderHeightLeft": {"name":"Shoulder height right","min": -2.00, "default": 0.00, "max": 1.00}
        }
    ,
    "54S":{
        
           "chestWidth": {"name" : "Chest width","min": 53.5, "default": 55.00, "max": 56.50},
           "waistWidth": {"name":"Waist width","min": 47.00, "default": 49.50, "max": 53.00},
           "jacketLength": {"name":"Jacket length","min": 26.50, "default": 31.25, "max": 35.00},
           "sleeveLengthRight": {"name":"Sleeve length right","min": 21.75, "default": 25.75, "max": 29.75},
           "sleeveLengthLeft": {"name":"Sleeve length left","min": 21.75, "default": 25.75, "max": 29.75},
           "hipWidth": {"name": "Hip Width" ,"min": 51.00, "default": 53.00, "max": 56.50},
           "shoulderWidth": {"name": "Shoulder width", "min": 18.75, "default": 20.75, "max": 22.75},
           "backWidth": {"name":"Back width","min": 10.00, "default": 10.50, "max": 11.25},
           "ventLength": {"name":"Vent length","min": 9.50, "default": 10.50, "max": 11.25},
           "frontLength": {"name":"Front length","min": 31.25, "default": 32.25, "max": 33.50},
           "bicepAround": {"name":"Bicep around","min": 20.50, "default": 21.00, "max": 22.00},
           "sleeveEdgeWidth": {"name":"Sleeve edge width","min": 12.00, "default": 13.00, "max": 14.50},
           "posture": {"name":"Posture","min": -2.00, "default": 0.00, "max": 2.00},
           "shoulderHeightRight": {"name":"Shoulder height right","min": -2.00, "default": 0.00, "max": 1.00},
           "shoulderHeightLeft": {"name":"Shoulder height right","min": -2.00, "default": 0.00, "max": 1.00}
        }
       ,
    "56S":{
        
           "chestWidth": {"name" : "Chest width","min": 55, "default": 56.50, "max": 58.00},
           "waistWidth": {"name":"Waist width","min": 49, "default": 51.00, "max": 54.50},
           "jacketLength": {"name":"Jacket length","min": 26.5, "default": 31.25, "max": 35.25},
           "sleeveLengthRight": {"name":"Sleeve length right","min": 22, "default": 26.00, "max": 30.00},
           "sleeveLengthLeft": {"name":"Sleeve length left","min": 22, "default": 26.00, "max": 30.00},
           "hipWidth": {"name": "Hip Width" ,"min": 52.5, "default": 55.00, "max": 58.00},
           "shoulderWidth": {"name": "Shoulder width", "min": 19.25, "default": 21.25, "max": 23.25},
           "backWidth": {"name":"Back width","min": 10.25, "default": 10.75, "max": 11.50},
           "ventLength": {"name":"Vent length","min": 9.75, "default": 10.50, "max": 11.50},
           "frontLength": {"name":"Front length","min": 31.5, "default": 32.50, "max": 33.50},
           "bicepAround": {"name":"Bicep around","min": 21, "default": 22.00, "max": 23.00},
           "sleeveEdgeWidth": {"name":"Sleeve edge width","min": 12, "default": 13.00, "max": 14.50},
           "posture": {"name":"Posture","min": -2, "default": 0, "max": 2},
           "shoulderHeightRight": {"name":"Shoulder height right","min": -2, "default": 0, "max": 1},
           "shoulderHeightLeft": {"name":"Shoulder height right","min": -2, "default": 0, "max": 1}
        }
       ,
    "30":  {
             "chestWidth": {"name" : "Chest width","min": 35.00, "default": 36.00, "max": 37.50},
             "waistWidth": {"name":"Waist width","min": 28.50, "default": 31.00, "max": 34.00},
             "jacketLength": {"name":"Jacket length","min": 23.25, "default": 28.00, "max": 31.75},
             "sleeveLengthRight": {"name":"Sleeve length right","min": 19.50, "default": 23.50, "max": 27.50},
             "sleeveLengthLeft": {"name":"Sleeve length left","min": 19.50, "default": 23.50, "max": 27.50},
             "hipWidth": {"name": "Hip Width" ,"min": 32.00, "default": 34.50, "max": 37.50},
             "shoulderWidth": {"name": "Shoulder width", "min": 14.25, "default": 16.25, "max": 18.25},
             "backWidth": {"name":"Back width","min": 7.00, "default": 7.50, "max": 8.25},
             "ventLength": {"name":"Vent length","min": 8.50, "default": 9.50, "max": 10.25},
             "frontLength": {"name":"Front length","min": 28.25, "default": 29.25, "max": 30.50},
             "bicepAround": {"name":"Bicep around","min": 12.50, "default": 13.00, "max": 13.50},
             "sleeveEdgeWidth": {"name":"Sleeve edge width","min": 9.00, "default": 10.50, "max": 12.00},
             "posture": {"name":"Posture","min": -2.00, "default": 0.00, "max": 2.00},
             "shoulderHeightRight": {"name":"Shoulder height right","min": -2.00, "default": 0.00, "max": 1.00},
             "shoulderHeightLeft": {"name":"Shoulder height right","min": -2.00, "default": 0.00, "max": 1.00}
           },
    "32":{
             "chestWidth": {"name" : "Chest width","min": 36.50, "default": 37.50, "max": 39.00},
             "waistWidth": {"name":"Waist width","min": 30.00, "default": 32.50, "max": 35.50},
             "jacketLength": {"name":"Jacket length","min": 23.50, "default": 28.50, "max": 32.25},
             "sleeveLengthRight": {"name":"Sleeve length right","min": 19.75, "default": 23.75, "max": 27.75},
             "sleeveLengthLeft": {"name":"Sleeve length left","min": 19.75, "default": 23.75, "max": 27.75},
             "hipWidth": {"name": "Hip Width" ,"min": 33.50, "default": 36.00, "max": 39.00},
             "shoulderWidth": {"name": "Shoulder width", "min": 7.25, "default": 7.75, "max": 8.50},
             "backWidth": {"name":"Back width","min": 8.50, "default": 9.50, "max": 10.25},
             "ventLength": {"name":"Vent length","min": 28.50, "default": 29.50, "max": 30.75},
             "frontLength": {"name":"Front length","min": 14.50, "default": 16.50, "max": 18.50},
             "bicepAround": {"name":"Bicep around","min": 13.00, "default": 13.50, "max": 14.50},
             "sleeveEdgeWidth": {"name":"Sleeve edge width","min": 9.00, "default": 10.50, "max": 12.00},
             "posture": {"name":"Posture","min": -2.00, "default": 0.00, "max": 2.00},
             "shoulderHeightRight": {"name":"Shoulder height right","min": -2.00, "default": 0.00, "max": 1.00},
             "shoulderHeightLeft": {"name":"Shoulder height right","min": -2.00, "default": 0.00, "max": 1.00}
       },
    "34" : {
             "chestWidth": {"name" : "Chest width","min": 37.50, "default": 39.00, "max": 40.50},
             "waistWidth": {"name":"Waist width","min": 31.50, "default": 34.00, "max": 37.00},
             "jacketLength": {"name":"Jacket length","min": 24.00, "default": 28.75, "max": 32.50},
             "sleeveLengthRight": {"name":"Sleeve length right","min": 20.00, "default": 24.00, "max": 28.00},
             "sleeveLengthLeft": {"name":"Sleeve length left","min": 20.00, "default": 24.00, "max": 28.00},
             "hipWidth": {"name": "Hip Width" ,"min": 15.00, "default": 17.00, "max": 18.75},
             "shoulderWidth": {"name": "Shoulder width", "min": 7.50, "default": 8.25, "max": 8.75},
             "backWidth": {"name":"Back width","min": 8.75, "default": 9.00, "max": 9.75},
             "ventLength": {"name":"Vent length","min": 9.00, "default": 9.50, "max": 10.50},
             "frontLength": {"name":"Front length","min": 13.00, "default": 14.00, "max": 15.00},
             "bicepAround": {"name":"Bicep around","min": 9.50, "default": 11.00, "max": 12.50},
             "sleeveEdgeWidth": {"name":"Sleeve edge width","min": -2.00, "default": 0.00, "max": 2.00},
             "posture": {"name":"Posture","min": -2.00, "default": 0.00, "max": 1.00},
             "shoulderHeightRight": {"name":"Shoulder height right","min": -2.00, "default": 0.00, "max": 1.00},
             "shoulderHeightLeft": {"name":"Shoulder height right","min": -2.00, "default": 0.00, "max": 1.00}     
        },
    "36":  {
        "chestWidth": {"name" : "Chest width","min": 39.00, "default": 40.50, "max": 42.00},
        "waistWidth": {"name":"Waist width","min": 33.00, "default": 35.50, "max": 38.50},
        "jacketLength": {"name":"Jacket length","min": 24.50, "default": 29.25, "max": 33.00},
        "sleeveLengthRight": {"name":"Sleeve length right","min": 20.75, "default": 24.50, "max": 28.50},
        "sleeveLengthLeft": {"name":"Sleeve length left","min": 20.75, "default": 24.50, "max": 28.50},
        "hipWidth": {"name": "Hip Width" ,"min": 15.50, "default": 17.50, "max": 19.25},
        "shoulderWidth": {"name": "Shoulder width", "min": 7.75, "default": 8.50, "max": 9.00},
        "backWidth": {"name":"Back width","min": 9.00, "default": 9.50, "max": 9.75},
        "ventLength": {"name":"Vent length","min": 9.50, "default": 10.00, "max": 10.50},
        "frontLength": {"name":"Front length","min": 14.00, "default": 15.00, "max": 15.50},
        "bicepAround": {"name":"Bicep around","min": 9.50, "default": 11.00, "max": 12.50},
        "sleeveEdgeWidth": {"name":"Sleeve edge width","min": -2.00, "default": 0.00, "max": 2.00},
        "posture": {"name":"Posture","min": -2.00, "default": 0.00, "max": 1.00},
        "shoulderHeightRight": {"name":"Shoulder height right","min": -2.00, "default": 0.00, "max": 1.00},
        "shoulderHeightLeft": {"name":"Shoulder height right","min": -2.00, "default": 0.00, "max": 1.00}
      },
    "38":  {
        "chestWidth": {"name" : "Chest width","min": 41.00, "default": 42.00, "max": 43.50},
        "waistWidth": {"name":"Waist width","min": 35.00, "default": 37.00, "max": 40.00},
        "jacketLength": {"name":"Jacket length","min": 24.75, "default": 29.50, "max": 33.50},
        "sleeveLengthRight": {"name":"Sleeve length right","min": 20.75, "default": 24.75, "max": 28.75},
        "sleeveLengthLeft": {"name":"Sleeve length left","min": 20.75, "default": 24.75, "max": 28.75},
        "hipWidth": {"name": "Hip Width" ,"min": 38.00, "default": 40.50, "max": 43.50},
        "shoulderWidth": {"name": "Shoulder width", "min": 15.75, "default": 17.75, "max": 19.50},
        "backWidth": {"name":"Back width","min": 8.00, "default": 8.50, "max": 9.25},
        "ventLength": {"name":"Vent length","min": 9.00, "default": 9.75, "max": 10.50},
        "frontLength": {"name":"Front length","min": 29.75, "default": 30.75, "max": 31.75},
        "bicepAround": {"name":"Bicep around","min": 15.00, "default": 15.50, "max": 16.50},
        "sleeveEdgeWidth": {"name":"Sleeve edge width","min": 10.00, "default": 11.00, "max": 12.50},
        "posture": {"name":"Posture","min": -2.00, "default": 0.00, "max": 2.00},
        "shoulderHeightRight": {"name":"Shoulder height right","min": -2.00, "default": 0.00, "max": 1.00},
        "shoulderHeightLeft": {"name":"Shoulder height right","min": -2.00, "default": 0.00, "max": 1.00}
     },
     "40": {
        "chestWidth": {"name" : "Chest width","min": 42.50, "default": 43.50, "max": 45.00},
        "waistWidth": {"name":"Waist width","min": 36.50, "default": 38.50, "max": 41.50},
        "jacketLength": {"name":"Jacket length","min": 25.25, "default": 30.00, "max": 33.75},
        "sleeveLengthRight": {"name":"Sleeve length right","min": 21.25, "default": 25.25, "max": 29.25},
        "sleeveLengthLeft": {"name":"Sleeve length left","min": 21.25, "default": 25.25, "max": 29.25},
        "hipWidth": {"name": "Hip Width" ,"min": 39.50, "default": 42.00, "max": 45.00},
        "shoulderWidth": {"name": "Shoulder width", "min": 16.25, "default": 18.25, "max": 20.00},
        "backWidth": {"name":"Back width","min": 8.25, "default": 8.75, "max": 9.50},
        "ventLength": {"name":"Vent length","min": 9.25, "default": 9.75, "max": 10.00},
        "frontLength": {"name":"Front length","min": 30.25, "default": 31.25, "max": 32.25},
        "bicepAround": {"name":"Bicep around","min": 15.50, "default": 16.50, "max": 17.00},
        "sleeveEdgeWidth": {"name":"Sleeve edge width","min": 10.50, "default": 11.50, "max": 13.00},
        "posture": {"name":"Posture","min": -2.00, "default": 0.00, "max": 2.00},
        "shoulderHeightRight": {"name":"Shoulder height right","min": -2.00, "default": 0.00, "max": 1.00},
        "shoulderHeightLeft": {"name":"Shoulder height right","min": -2.00, "default": 0.00, "max": 1.00}
     },
     "42" : {
        "chestWidth": {"name" : "Chest width","min": 44.00, "default": 45.00, "max": 47.00},
        "waistWidth": {"name":"Waist width","min": 37.50, "default": 40.00, "max": 43.00},
        "jacketLength": {"name":"Jacket length","min": 25.50, "default": 30.50, "max": 34.25},
        "sleeveLengthRight": {"name":"Sleeve length right","min": 21.50, "default": 25.50, "max": 29.50},
        "sleeveLengthLeft": {"name":"Sleeve length left","min": 21.50, "default": 25.50, "max": 29.50},
        "hipWidth": {"name": "Hip Width" ,"min": 16.50, "default": 18.50, "max": 20.50},
        "shoulderWidth": {"name": "Shoulder width", "min": 8.50, "default": 9.00, "max": 9.50},
        "backWidth": {"name":"Back width","min": 9.25, "default": 10.00, "max": 10.75},
        "ventLength": {"name":"Vent length","min": 30.50, "default": 31.50, "max": 32.50},
        "frontLength": {"name":"Front length","min": 16.50, "default": 17.00, "max": 18.00},
        "bicepAround": {"name":"Bicep around","min": 10.50, "default": 11.50, "max": 13.00},
        "sleeveEdgeWidth": {"name":"Sleeve edge width","min": -2.00, "default": 0.00, "max": 2.00},
        "posture": {"name":"Posture","min": -2.00, "default": 0.00, "max": 2.00},
        "shoulderHeightRight": {"name":"Shoulder height right","min": -2.00, "default": 0.00, "max": 1.00},
        "shoulderHeightLeft": {"name":"Shoulder height right","min": -2.00, "default": 0.00, "max": 1.00}
     },
"44": {
    "chestWidth": {"name" : "Chest width","min": 45.50, "default": 47.00, "max": 48.50},
    "waistWidth": {"name":"Waist width","min": 39.00, "default": 41.50, "max": 45.00},
    "jacketLength": {"name":"Jacket length","min": 26.00, "default": 30.75, "max": 34.50},
    "sleeveLengthRight": {"name":"Sleeve length right","min": 21.75, "default": 25.75, "max": 29.75},
    "sleeveLengthLeft": {"name":"Sleeve length left","min": 21.75, "default": 25.75, "max": 29.75},
    "hipWidth": {"name": "Hip Width" ,"min": 43.00, "default": 45.00, "max": 48.50},
    "shoulderWidth": {"name": "Shoulder width", "min": 17.00, "default": 18.75, "max": 20.75},
    "backWidth": {"name":"Back width","min": 8.75, "default": 9.50, "max": 10.00},
    "ventLength": {"name":"Vent length","min": 9.50, "default": 10.25, "max": 11.00},
    "frontLength": {"name":"Front length","min": 11.00, "default": 12.00, "max": 13.00},
    "bicepAround": {"name":"Bicep around","min": -2.00, "default": 0.00, "max": 2.00},
    "sleeveEdgeWidth": {"name":"Sleeve edge width","min": -2.00, "default": 0.00, "max": 2.00},
    "posture": {"name":"Posture","min": -2.00, "default": 0.00, "max": 1.00},
    "shoulderHeightRight": {"name":"Shoulder height right","min": -2.00, "default": 0.00, "max": 1.00},
    "shoulderHeightLeft": {"name":"Shoulder height right","min": -2.00, "default": 0.00, "max": 1.00}
  },
  "46":{
    "chestWidth": {"name" : "Chest width","min": 47.00, "default": 48.50, "max": 50.00},
    "waistWidth": {"name":"Waist width","min": 41.00, "default": 43.00, "max": 46.50},
    "jacketLength": {"name":"Jacket length","min": 26.50, "default": 31.25, "max": 35.00},
    "sleeveLengthRight": {"name":"Sleeve length right","min": 22.00, "default": 26.00, "max": 30.00},
    "sleeveLengthLeft": {"name":"Sleeve length left","min": 22.00, "default": 26.00, "max": 30.00},
    "hipWidth": {"name": "Hip Width" ,"min": 44.50, "default": 47.00, "max": 50.00},
    "shoulderWidth": {"name": "Shoulder width", "min": 17.50, "default": 19.25, "max": 21.25},
    "backWidth": {"name":"Back width","min": 9.00, "default": 9.50, "max": 10.25},
    "ventLength": {"name":"Vent length","min": 9.50, "default": 10.50, "max": 11.25},
    "frontLength": {"name":"Front length","min": 11.00, "default": 12.00, "max": 13.00},
    "bicepAround": {"name":"Bicep around","min": -2.00, "default": 0.00, "max": 2.00},
    "sleeveEdgeWidth": {"name":"Sleeve edge width","min": -2.00, "default": 0.00, "max": 2.00},
    "posture": {"name":"Posture","min": -2.00, "default": 0.00, "max": 1.00},
    "shoulderHeightRight": {"name":"Shoulder height right","min": -2.00, "default": 0.00, "max": 1.00},
    "shoulderHeightLeft": {"name":"Shoulder height right","min": -2.00, "default": 0.00, "max": 1.00}
  },
  "48": {
    "chestWidth": {"name" : "Chest width","min": 49.00, "default": 50.00, "max": 51.50},
    "waistWidth": {"name":"Waist width","min": 42.50, "default": 45.00, "max": 48.00},
    "jacketLength": {"name":"Jacket length","min": 26.75, "default": 31.50, "max": 35.50},
    "sleeveLengthRight": {"name":"Sleeve length right","min": 22.25, "default": 26.25, "max": 30.25},
    "sleeveLengthLeft": {"name":"Sleeve length left","min": 22.25, "default": 26.25, "max": 30.25},
    "hipWidth": {"name": "Hip Width" ,"min": 46.00, "default": 48.50, "max": 51.50},
    "shoulderWidth": {"name": "Shoulder width", "min": 17.75, "default": 19.50, "max": 21.50},
    "backWidth": {"name":"Back width","min": 9.25, "default": 9.75, "max": 10.50},
    "ventLength": {"name":"Vent length","min": 9.50, "default": 10.50, "max": 11.25},
    "frontLength": {"name":"Front length","min": 31.50, "default": 32.50, "max": 33.75},
    "bicepAround": {"name":"Bicep around","min": 18.50, "default": 19.00, "max": 20.00},
    "sleeveEdgeWidth": {"name":"Sleeve edge width","min": 11.00, "default": 12.50, "max": 13.50},
    "posture": {"name":"Posture","min": -2.00, "default": 0.00, "max": 2.00},
    "shoulderHeightRight": {"name":"Shoulder height right","min": -2.00, "default": 0.00, "max": 1.00},
    "shoulderHeightLeft": {"name":"Shoulder height right","min": -2.00, "default": 0.00, "max": 1.00}
  },
  "50":{
    "chestWidth": {"name" : "Chest width","min": 50.50, "default": 51.50, "max": 53.00},
    "waistWidth": {"name":"Waist width","min": 44.00, "default": 46.50, "max": 49.50},
    "jacketLength": {"name":"Jacket length","min": 27.25, "default": 31.75, "max": 35.75},
    "sleeveLengthRight": {"name":"Sleeve length right","min": 22.50, "default": 26.50, "max": 30.50},
    "sleeveLengthLeft": {"name":"Sleeve length left","min": 22.50, "default": 26.50, "max": 30.50},
    "hipWidth": {"name": "Hip Width" ,"min": 47.50, "default": 50.00, "max": 53.00},
    "shoulderWidth": {"name": "Shoulder width", "min": 18.25, "default": 20.00, "max": 22.00},
    "backWidth": {"name":"Back width","min": 9.50, "default": 10.00, "max": 10.50},
    "ventLength": {"name":"Vent length","min": 9.75, "default": 10.50, "max": 11.50},
    "frontLength": {"name":"Front length","min": 32.00, "default": 33.00, "max": 34.25},
    "bicepAround": {"name":"Bicep around","min": 19.00, "default": 20.00, "max": 21.00},
    "sleeveEdgeWidth": {"name":"Sleeve edge width","min": 11.50, "default": 12.50, "max": 14.00},
    "posture": {"name":"Posture","min": -2.00, "default": 0.00, "max": 2.00},
    "shoulderHeightRight": {"name":"Shoulder height right","min": -2.00, "default": 0.00, "max": 1.00},
    "shoulderHeightLeft": {"name":"Shoulder height right","min": -2.00, "default": 0.00, "max": 1.00}
  },
  "52": {
    "chestWidth": {"name" : "Chest width","min": 52.00, "default": 53.00, "max": 55.00},
    "waistWidth": {"name":"Waist width","min": 45.50, "default": 48.00, "max": 51.00},
    "jacketLength": {"name":"Jacket length","min": 27.50, "default": 32.00, "max": 36.00},
    "sleeveLengthRight": {"name":"Sleeve length right","min": 22.50, "default": 26.50, "max": 30.50},
    "sleeveLengthLeft": {"name":"Sleeve length left","min": 22.50, "default": 26.50, "max": 30.50},
    "hipWidth": {"name": "Hip Width" ,"min": 49.00, "default": 51.50, "max": 55.00},
    "shoulderWidth": {"name": "Shoulder width", "min": 18.50, "default": 20.50, "max": 22.50},
    "backWidth": {"name":"Back width","min": 9.50, "default": 10.25, "max": 10.75},
    "ventLength": {"name":"Vent length","min": 9.75, "default": 10.50, "max": 11.50},
    "frontLength": {"name":"Front length","min": 20.00, "default": 21.00, "max": 21.50},
    "bicepAround": {"name":"Bicep around","min": 11.50, "default": 12.50, "max": 14.00},
    "sleeveEdgeWidth": {"name":"Sleeve edge width","min": -2.00, "default": 0.00, "max": 2.00},
    "posture": {"name":"Posture","min": -2.00, "default": 0.00, "max": 1.00},
    "shoulderHeightRight": {"name":"Shoulder height right","min": -2.00, "default": 0.00, "max": 1.00},
    "shoulderHeightLeft": {"name":"Shoulder height right","min": -2.00, "default": 0.00, "max": 1.00}
 },
"54" :  {
    "chestWidth": {"name" : "Chest width","min": 53.50, "default": 55.00, "max": 56.50},
    "waistWidth": {"name":"Waist width","min": 47.00, "default": 49.50, "max": 53.00},
    "jacketLength": {"name":"Jacket length","min": 27.50, "default": 32.25, "max": 36.25},
    "sleeveLengthRight": {"name":"Sleeve length right","min": 22.75, "default": 26.75, "max": 30.75},
    "sleeveLengthLeft": {"name":"Sleeve length left","min": 22.75, "default": 26.75, "max": 30.75},
    "hipWidth": {"name": "Hip Width" ,"min": 51.00, "default": 53.00, "max": 56.50},
    "shoulderWidth": {"name": "Shoulder width", "min": 18.75, "default": 20.75, "max": 22.75},
    "backWidth": {"name":"Back width","min": 10.00, "default": 10.50, "max": 11.25},
    "ventLength": {"name":"Vent length","min": 10.00, "default": 10.75, "max": 11.50},
    "frontLength": {"name":"Front length","min": 20.50, "default": 21.00, "max": 22.00},
    "bicepAround": {"name":"Bicep around","min": 12.00, "default": 13.00, "max": 14.50},
    "sleeveEdgeWidth": {"name":"Sleeve edge width","min": -2.00, "default": 0.00, "max": 2.00},
    "posture": {"name":"Posture","min": -2.00, "default": 0.00, "max": 1.00},
    "shoulderHeightRight": {"name":"Shoulder height right","min": -2.00, "default": 0.00, "max": 1.00},
    "shoulderHeightLeft": {"name":"Shoulder height right","min": -2.00, "default": 0.00, "max": 1.00}
 },
 "56": {
    "chestWidth": {"name" : "Chest width","min": 55.00, "default": 56.50, "max": 58.00},
    "waistWidth": {"name":"Waist width","min": 49.00, "default": 51.00, "max": 54.50},
    "jacketLength": {"name":"Jacket length","min": 27.75, "default": 32.50, "max": 36.50},
    "sleeveLengthRight": {"name":"Sleeve length right","min": 23.00, "default": 27.00, "max": 31.00},
    "sleeveLengthLeft": {"name":"Sleeve length left","min": 23.00, "default": 27.00, "max": 31.00},
    "hipWidth": {"name": "Hip Width" ,"min": 52.50, "default": 55.00, "max": 58.00},
    "shoulderWidth": {"name": "Shoulder width", "min": 19.25, "default": 21.25, "max": 23.25},
    "backWidth": {"name":"Back width","min": 10.25, "default": 10.75, "max": 11.50},
    "ventLength": {"name":"Vent length","min": 10.25, "default": 11.00, "max": 11.75},
    "frontLength": {"name":"Front length","min": 32.50, "default": 33.50, "max": 34.75},
    "bicepAround": {"name":"Bicep around","min": 21.00, "default": 22.00, "max": 23.00},
    "sleeveEdgeWidth": {"name":"Sleeve edge width","min": 12.00, "default": 13.00, "max": 14.50},
    "posture": {"name":"Posture","min": -2.00, "default": 0.00, "max": 2.00},
    "shoulderHeightRight": {"name":"Shoulder height right","min": -2.00, "default": 0.00, "max": 1.00},
    "shoulderHeightLeft": {"name":"Shoulder height right","min": -2.00, "default": 0.00, "max": 1.00}
  },
  "58": {
    "chestWidth": {"name" : "Chest width","min": 57.00, "default": 58.00, "max": 59.50},
    "waistWidth": {"name":"Waist width","min": 50.50, "default": 53.00, "max": 56.00},
    "jacketLength": {"name":"Jacket length","min": 28.00, "default": 32.50, "max": 36.50},
    "sleeveLengthRight": {"name":"Sleeve length right","min": 23.25, "default": 27.25, "max": 31.25},
    "sleeveLengthLeft": {"name":"Sleeve length left","min": 23.25, "default": 27.25, "max": 31.25},
    "hipWidth": {"name": "Hip Width" ,"min": 54.00, "default": 56.50, "max": 59.50},
    "shoulderWidth": {"name": "Shoulder width", "min": 19.50, "default": 21.50, "max": 23.50},
    "backWidth": {"name":"Back width","min": 10.50, "default": 11.00, "max": 11.50},
    "ventLength": {"name":"Vent length","min": 10.25, "default": 11.00, "max": 11.75},
    "frontLength": {"name":"Front length","min": 32.75, "default": 33.75, "max": 35.00},
    "bicepAround": {"name":"Bicep around","min": 22.00, "default": 23.00, "max": 23.50},
    "sleeveEdgeWidth": {"name":"Sleeve edge width","min": 12.50, "default": 13.00, "max": 15.00},
    "posture": {"name":"Posture","min": -2.00, "default": 0.00, "max": 2.00},
    "shoulderHeightRight": {"name":"Shoulder height right","min": -2.00, "default": 0.00, "max": 1.00},
    "shoulderHeightLeft": {"name":"Shoulder height right","min": -2.00, "default": 0.00, "max": 1.00}
  },
  "60":{
    "chestWidth": {"name" : "Chest width","min": 58.50, "default": 59.50, "max": 61.00},
    "waistWidth": {"name":"Waist width","min": 52.00, "default": 54.50, "max": 57.50},
    "jacketLength": {"name":"Jacket length","min": 28.25, "default": 32.75, "max": 36.75},
    "sleeveLengthRight": {"name":"Sleeve length right","min": 23.50, "default": 27.50, "max": 31.25},
    "sleeveLengthLeft": {"name":"Sleeve length left","min": 23.50, "default": 27.50, "max": 31.25},
    "hipWidth": {"name": "Hip Width" ,"min": 55.50, "default": 58.00, "max": 61.00},
    "shoulderWidth": {"name": "Shoulder width", "min": 20.00, "default": 22.00, "max": 24.00},
    "backWidth": {"name":"Back width","min": 10.50, "default": 11.25, "max": 11.75},
    "ventLength": {"name":"Vent length","min": 10.50, "default": 11.25, "max": 12.00},
    "frontLength": {"name":"Front length","min": 33.00, "default": 34.00, "max": 35.25},
    "bicepAround": {"name":"Bicep around","min": 23.00, "default": 23.50, "max": 24.50},
    "sleeveEdgeWidth": {"name":"Sleeve edge width","min": -2.00, "default": 0.00, "max": 2.00},
    "posture": {"name":"Posture","min": -2.00, "default": 0.00, "max": 1.00},
    "shoulderHeightRight": {"name":"Shoulder height right","min": -2.00, "default": 0.00, "max": 1.00},
    "shoulderHeightLeft": {"name":"Shoulder height right","min": -2.00, "default": 0.00, "max": 1.00}
 },
 "36L":{
    "chestWidth": {"name" : "Chest width","min": 39, "default": 40, "max": 41.5},
    "waistWidth": {"name":"Waist width","min": 32.5, "default": 35, "max": 37.5},
    "jacketLength": {"name":"Jacket length","min": 25.5, "default": 30.5, "max": 34.25},
    "sleeveLengthRight": {"name":"Sleeve length right","min": 21.5, "default": 25.5, "max": 29.5},
    "sleeveLengthLeft": {"name":"Sleeve length left","min": 21.5, "default": 25.5, "max": 29.5},
    "hipWidth": {"name": "Hip Width" ,"min": 15.5, "default": 17.5, "max": 19.25},
    "shoulderWidth": {"name": "Shoulder width", "min": 7.75, "default": 8.5, "max": 9},
    "backWidth": {"name":"Back width","min": 9, "default": 9.25, "max": 9.5},
    "ventLength": {"name":"Vent length","min": 10, "default": 10.75, "max": 11},
    "frontLength": {"name":"Front length","min": 30.5, "default": 31.5, "max": 32.5},
    "bicepAround": {"name":"Bicep around","min": 14, "default": 15, "max": 15.5},
    "sleeveEdgeWidth": {"name":"Sleeve edge width","min": 9.5, "default": 10, "max": 11},
    "posture": {"name":"Posture","min": -2, "default": 0, "max": 2},
    "shoulderHeightRight": {"name":"Shoulder height right","min": -2, "default": 0, "max": 1},
    "shoulderHeightLeft": {"name":"Shoulder height right","min": -2, "default": 0, "max": 1}
  },
  "38L":{
    "chestWidth": {"name" : "Chest width","min": 40.5, "default": 41.5, "max": 43},
    "waistWidth": {"name":"Waist width","min": 34, "default": 36.5, "max": 39},
    "jacketLength": {"name":"Jacket length","min": 26, "default": 30.75, "max": 34.5},
    "sleeveLengthRight": {"name":"Sleeve length right","min": 21.75, "default": 25.75, "max": 29.75},
    "sleeveLengthLeft": {"name":"Sleeve length left","min": 21.75, "default": 25.75, "max": 29.75},
    "hipWidth": {"name": "Hip Width" ,"min": 15.75, "default": 17.75, "max": 19.5},
    "shoulderWidth": {"name": "Shoulder width", "min": 8, "default": 8.5, "max": 9.25},
    "backWidth": {"name":"Back width","min": 9.5, "default": 9.75, "max": 10.25},
    "ventLength": {"name":"Vent length","min": 11, "default": 31, "max": 31.75},
    "frontLength": {"name":"Front length","min": 33, "default": 33, "max": 33},
    "bicepAround": {"name":"Bicep around","min": 15, "default": 15.5, "max": 16.5},
    "sleeveEdgeWidth": {"name":"Sleeve edge width","min": 10, "default": 11, "max": 12.5},
    "posture": {"name":"Posture","min": -2, "default": 0, "max": 2},
    "shoulderHeightRight": {"name":"Shoulder height right","min": -2, "default": 0, "max": 1},
    "shoulderHeightLeft": {"name":"Shoulder height right","min": -2, "default": 0, "max": 1}
  },
  "40L":{
    "chestWidth": {"name" : "Chest width","min": 42, "default": 43, "max": 45},
    "waistWidth": {"name":"Waist width","min": 35.5, "default": 37, "max": 41},
    "jacketLength": {"name":"Jacket length","min": 26.5, "default": 31.25, "max": 35},
    "sleeveLengthRight": {"name":"Sleeve length right","min": 22.25, "default": 26.25, "max": 30.25},
    "sleeveLengthLeft": {"name":"Sleeve length left","min": 22.25, "default": 26.25, "max": 30.25},
    "hipWidth": {"name": "Hip Width" ,"min": 16.25, "default": 18.25, "max": 20},
    "shoulderWidth": {"name": "Shoulder width", "min": 8.25, "default": 8.75, "max": 9.5},
    "backWidth": {"name":"Back width","min": 9.5, "default": 9.5, "max": 10.5},
    "ventLength": {"name":"Vent length","min": 10.5, "default": 11.25, "max": 13},
    "frontLength": {"name":"Front length","min": 15.5, "default": 16.5, "max": 17},
    "bicepAround": {"name":"Bicep around","min": 10.5, "default": 11.5, "max": 13},
    "sleeveEdgeWidth": {"name":"Sleeve edge width","min": -2, "default": 0, "max": 2},
    "posture": {"name":"Posture","min": -2, "default": 0, "max": 1},
    "shoulderHeightRight": {"name":"Shoulder height right","min": -2, "default": 0, "max": 1},
    "shoulderHeightLeft": {"name":"Shoulder height right","min": -2, "default": 0, "max": 1}
 },
 "42L":{
    "chestWidth": {"name" : "Chest width","min": 43.5, "default": 45, "max": 46.5},
    "waistWidth": {"name":"Waist width","min": 37, "default": 39, "max": 42.5},
    "jacketLength": {"name":"Jacket length","min": 26.75, "default": 31.5, "max": 35.5},
    "sleeveLengthRight": {"name":"Sleeve length right","min": 22.5, "default": 26.5, "max": 30.5},
    "sleeveLengthLeft": {"name":"Sleeve length left","min": 22.5, "default": 26.5, "max": 30.5},
    "hipWidth": {"name": "Hip Width" ,"min": 16.5, "default": 18.5, "max": 20.5},
    "shoulderWidth": {"name": "Shoulder width", "min": 8.5, "default": 9, "max": 9.5},
    "backWidth": {"name":"Back width","min": 9.5, "default": 9.5, "max": 10.5},
    "ventLength": {"name":"Vent length","min": 10.5, "default": 11.25, "max": 13},
    "frontLength": {"name":"Front length","min": 16.5, "default": 17, "max": 18},
    "bicepAround": {"name":"Bicep around","min": 10.5, "default": 11.5, "max": 13},
    "sleeveEdgeWidth": {"name":"Sleeve edge width","min": -2, "default": 0, "max": 2},
    "posture": {"name":"Posture","min": -2, "default": 0, "max": 1},
    "shoulderHeightRight": {"name":"Shoulder height right","min": -2, "default": 0, "max": 1},
    "shoulderHeightLeft": {"name":"Shoulder height right","min": -2, "default": 0, "max": 1}
 },
 "44L": {
    "chestWidth": {"name" : "Chest width","min": 45, "default": 46.5, "max": 48},
    "waistWidth": {"name":"Waist width","min": 38.5, "default": 41, "max": 44},
    "jacketLength": {"name":"Jacket length","min": 27.25, "default": 31.75, "max": 35.75},
    "sleeveLengthRight": {"name":"Sleeve length right","min": 22.75, "default": 26.75, "max": 30.75},
    "sleeveLengthLeft": {"name":"Sleeve length left","min": 22.75, "default": 26.75, "max": 30.75},
    "hipWidth": {"name": "Hip Width" ,"min": 17, "default": 18.75, "max": 20.75},
    "shoulderWidth": {"name": "Shoulder width", "min": 8.75, "default": 9.5, "max": 10},
    "backWidth": {"name":"Back width","min": 9.75, "default": 10.5, "max": 11.5},
    "ventLength": {"name":"Vent length","min": 32, "default": 33, "max": 34.25},
    "frontLength": {"name":"Front length","min": 17, "default": 17.5, "max": 18.5},
    "bicepAround": {"name":"Bicep around","min": 11, "default": 12, "max": 13},
    "sleeveEdgeWidth": {"name":"Sleeve edge width","min": -2, "default": 0, "max": 2},
    "posture": {"name":"Posture","min": -2, "default": 0, "max": 1},
    "shoulderHeightRight": {"name":"Shoulder height right","min": -2, "default": 0, "max": 1},
    "shoulderHeightLeft": {"name":"Shoulder height right","min": -2, "default": 0, "max": 1}
  },
  "46L":{
    "chestWidth": {"name" : "Chest width","min": 47, "default": 48, "max": 49.5},
    "waistWidth": {"name":"Waist width","min": 40, "default": 42.5, "max": 45.5},
    "jacketLength": {"name":"Jacket length","min": 27.5, "default": 32.25, "max": 36.25},
    "sleeveLengthRight": {"name":"Sleeve length right","min": 23.25, "default": 27.25, "max": 31.25},
    "sleeveLengthLeft": {"name":"Sleeve length left","min": 23.25, "default": 27.25, "max": 31.25},
    "hipWidth": {"name": "Hip Width" ,"min": 17.5, "default": 19.25, "max": 21.25},
    "shoulderWidth": {"name": "Shoulder width", "min": 9, "default": 9.5, "max": 10.25},
    "backWidth": {"name":"Back width","min": 9.75, "default": 10.5, "max": 11.5},
    "ventLength": {"name":"Vent length","min": 32.5, "default": 33.5, "max": 34.5},
    "frontLength": {"name":"Front length","min": 17.5, "default": 18.5, "max": 19},
    "bicepAround": {"name":"Bicep around","min": 11, "default": 12, "max": 13},
    "sleeveEdgeWidth": {"name":"Sleeve edge width","min": -2, "default": 0, "max": 2},
    "posture": {"name":"Posture","min": -2, "default": 0, "max": 1},
    "shoulderHeightRight": {"name":"Shoulder height right","min": -2, "default": 0, "max": 1},
    "shoulderHeightLeft": {"name":"Shoulder height right","min": -2, "default": 0, "max": 1}
  },
  "48L":{
    "chestWidth": {"name" : "Chest width","min": 48.5, "default": 49.5, "max": 51},
    "waistWidth": {"name":"Waist width","min": 41.5, "default": 44, "max": 47},
    "jacketLength": {"name":"Jacket length","min": 28, "default": 32.5, "max": 36.5},
    "sleeveLengthRight": {"name":"Sleeve length right","min": 23.5, "default": 27.5, "max": 31.5},
    "sleeveLengthLeft": {"name":"Sleeve length left","min": 23.5, "default": 27.5, "max": 31.5},
    "hipWidth": {"name": "Hip Width" ,"min": 23.5, "default": 27.5, "max": 31.5},
    "shoulderWidth": {"name": "Shoulder width", "min": 9.25, "default": 9.75, "max": 10.5},
    "backWidth": {"name":"Back width","min": 9.5, "default": 10, "max": 10.75},
    "ventLength": {"name":"Vent length","min": 10, "default": 11, "max": 11.75},
    "frontLength": {"name":"Front length","min": 11, "default": 12.5, "max": 13.5},
    "bicepAround": {"name":"Bicep around","min": 11, "default": 12.5, "max": 14},
    "sleeveEdgeWidth": {"name":"Sleeve edge width","min": -2, "default": 0, "max": 2},
    "posture": {"name":"Posture","min": -2, "default": 0, "max": 1},
    "shoulderHeightRight": {"name":"Shoulder height right","min": -2, "default": 0, "max": 1},
    "shoulderHeightLeft": {"name":"Shoulder height right","min": -2, "default": 0, "max": 1}
  },
  "50L":{
    "chestWidth": {"name" : "Chest width","min": 50, "default": 51, "max": 53},
    "waistWidth": {"name":"Waist width","min": 43, "default": 45.5, "max": 49},
    "jacketLength": {"name":"Jacket length","min": 28.5, "default": 33, "max": 37},
    "sleeveLengthRight": {"name":"Sleeve length right","min": 24, "default": 28, "max": 31.75},
    "sleeveLengthLeft": {"name":"Sleeve length left","min": 24, "default": 28, "max": 31.75},
    "hipWidth": {"name": "Hip Width" ,"min": 24, "default": 28, "max": 31.75},
    "shoulderWidth": {"name": "Shoulder width", "min": 9.5, "default": 10, "max": 10.5},
    "backWidth": {"name":"Back width","min": 10, "default": 10.25, "max": 11},
    "ventLength": {"name":"Vent length","min": 11, "default": 11.75, "max": 12},
    "frontLength": {"name":"Front length","min": 11.5, "default": 12.5, "max": 13.5},
    "bicepAround": {"name":"Bicep around","min": 11.5, "default": 12.5, "max": 14},
    "sleeveEdgeWidth": {"name":"Sleeve edge width","min": -2, "default": 0, "max": 2},
    "posture": {"name":"Posture","min": -2, "default": 0, "max": 1},
    "shoulderHeightRight": {"name":"Shoulder height right","min": -2, "default": 0, "max": 1},
    "shoulderHeightLeft": {"name":"Shoulder height right","min": -2, "default": 0, "max": 1}
  },
  "52L":{
    "chestWidth": {"name" : "Chest width","min": 51.5, "default": 53, "max": 54.5},
    "waistWidth": {"name":"Waist width","min": 45, "default": 47, "max": 50.5},
    "jacketLength": {"name":"Jacket length","min": 28.5, "default": 33.25, "max": 37.25},
    "sleeveLengthRight": {"name":"Sleeve length right","min": 24.5, "default": 28.5, "max": 32.25},
    "sleeveLengthLeft": {"name":"Sleeve length left","min": 24.5, "default": 28.5, "max": 32.25},
    "hipWidth": {"name": "Hip Width" ,"min": 48.5, "default": 51, "max": 54},
    "shoulderWidth": {"name": "Shoulder width", "min": 18.5, "default": 20.5, "max": 22.5},
    "backWidth": {"name":"Back width","min": 9.5, "default": 10.25, "max": 10.75},
    "ventLength": {"name":"Vent length","min": 10, "default": 10.5, "max": 11.25},
    "frontLength": {"name":"Front length","min": 10.5, "default": 11, "max": 11.5},
    "bicepAround": {"name":"Bicep around","min": 11.75, "default": 12.25, "max": 12.5},
    "sleeveEdgeWidth": {"name":"Sleeve edge width","min": 12, "default": 13, "max": 14},
    "posture": {"name":"Posture","min": -2, "default": 0, "max": 2},
    "shoulderHeightRight": {"name":"Shoulder height right","min": -2, "default": 0, "max": 1},
    "shoulderHeightLeft": {"name":"Shoulder height right","min": -2, "default": 0, "max": 1}
  },
  "54L":{
    "chestWidth": {"name" : "Chest width","min": 53, "default": 54.5, "max": 56},
    "waistWidth": {"name":"Waist width","min": 46.5, "default": 49, "max": 52},
    "jacketLength": {"name":"Jacket length","min": 28.75, "default": 33.5, "max": 37.5},
    "sleeveLengthRight": {"name":"Sleeve length right","min": 24.5, "default": 28.5, "max": 32.5},
    "sleeveLengthLeft": {"name":"Sleeve length left","min": 24.5, "default": 28.5, "max": 32.5},
    "hipWidth": {"name": "Hip Width" ,"min": 50, "default": 52.5, "max": 57.5},
    "shoulderWidth": {"name": "Shoulder width", "min": 18.75, "default": 20.75, "max": 22.75},
    "backWidth": {"name":"Back width","min": 10, "default": 10.5, "max": 11.25},
    "ventLength": {"name":"Vent length","min": 10, "default": 10.5, "max": 11.5},
    "frontLength": {"name":"Front length","min": 10.5, "default": 11, "max": 11.5},
    "bicepAround": {"name":"Bicep around","min": 12, "default": 12.5, "max": 13},
    "sleeveEdgeWidth": {"name":"Sleeve edge width","min": 13, "default": 14, "max": 14.5},
    "posture": {"name":"Posture","min": -2, "default": 0, "max": 2},
    "shoulderHeightRight": {"name":"Shoulder height right","min": -2, "default": 0, "max": 1},
    "shoulderHeightLeft": {"name":"Shoulder height right","min": -2, "default": 0, "max": 1}
  }
}